LICENSE
README.md
pyproject.toml
armory/data.py
armory/dataset.py
armory/evaluation.py
armory/labels.py
armory/logs.py
armory/metric.py
armory/perturbation.py
armory/track.py
armory/utils.py
armory/version.py
armory/engine/__init__.py
armory/engine/adversarial_dataset.py
armory/engine/evaluation.py
armory/engine/evaluation_module.py
armory/engine/optimization.py
armory/engine/optimization_module.py
armory/experimental/README.md
armory/experimental/__init__.py
armory/experimental/patch.py
armory/experimental/transforms.py
armory/export/__init__.py
armory/export/base.py
armory/export/captum.py
armory/export/criteria.py
armory/export/image_classification.py
armory/export/object_detection.py
armory/export/sink.py
armory/export/xaitksaliency.py
armory/export/drise/__init__.py
armory/export/drise/exporter.py
armory/export/drise/impl.py
armory/metrics/__init__.py
armory/metrics/compute.py
armory/metrics/detection.py
armory/metrics/perturbation.py
armory/metrics/tide.py
armory/model/__init__.py
armory/model/base.py
armory/model/image_classification/__init__.py
armory/model/image_classification/image_classifier.py
armory/model/object_detection/__init__.py
armory/model/object_detection/object_detector.py
armory/model/object_detection/yolos_transformer.py
armory/model/object_detection/yolov4_object_detector.py
armory/model/object_detection/yolov5_object_detector.py
armory/results/__init__.py
armory/results/plots.py
armory/results/results.py
armory/results/utils.py
armory_library-24.6.1.dist-info/METADATA
armory_library-24.6.1.dist-info/WHEEL
armory_library-24.6.1.dist-info/entry_points.txt
armory_library-24.6.1.dist-info/licenses/LICENSE
armory_library-24.6.1.dist-info/RECORD
